{
	"objects": [
		{
			"id": "64d2a79f-60ee-4da9-aa2c-96a0970f0581",
			"class_id": "06852717-c0c4-4200-a1ae-3648413cc30a",
			"tracking_id": 1,
			"class_name": "c_3_01",
			"annotation_type": "box",
			"annotation": {
				"coord": {
					"x": 417.47179201525876,
					"y": 132.45252119908886,
					"width": 279.99073947402144,
					"height": 342.8792844730692
				},
				"meta": {
					"z_index": 1,
					"visible": true,
					"alpha": 1,
					"color": "#D1C8FF"
				}
			},
			"properties": []
		},
		{
			"id": "021b3ff6-0938-4efc-a92d-77f2ad20b167",
			"class_id": "06852717-c0c4-4200-a1ae-3648413cc30a",
			"tracking_id": 2,
			"class_name": "c_3_01",
			"annotation_type": "box",
			"annotation": {
				"coord": {
					"x": 689.111998483663,
					"y": 248.61409087490563,
					"width": 385.048156228519,
					"height": 211.83604153702584
				},
				"meta": {
					"z_index": 2,
					"visible": true,
					"alpha": 1,
					"color": "#D1C8FF"
				}
			},
			"properties": []
		},
		{
			"id": "d9a275cb-259f-4c00-8610-4b744c1c186f",
			"class_id": "916ce2cb-6bee-423f-98a5-61dc70f57c53",
			"tracking_id": 3,
			"class_name": "c_3",
			"annotation_type": "box",
			"annotation": {
				"coord": {
					"x": 1213.907072473822,
					"y": 38.1679680488124,
					"width": 359.6286541034299,
					"height": 287.9649338662484
				},
				"meta": {
					"z_index": 3,
					"visible": false,
					"alpha": 1,
					"color": "#FFDFD5"
				}
			},
			"properties": []
		},
		{
			"id": "e3f945f2-e5e3-4ce0-9c57-69a4c45eefee",
			"class_id": "06852717-c0c4-4200-a1ae-3648413cc30a",
			"tracking_id": 4,
			"class_name": "c_3_01",
			"annotation_type": "box",
			"annotation": {
				"coord": {
					"x": 1233.2824612303657,
					"y": 110.91703037036723,
					"width": 503.1808554429999,
					"height": 422.8537616855816
				},
				"meta": {
					"z_index": 4,
					"visible": false,
					"alpha": 1,
					"color": "#D1C8FF"
				}
			},
			"properties": []
		},
		{
			"id": "fe55c343-2407-4286-8c24-1f3a56e3b972",
			"class_id": "916ce2cb-6bee-423f-98a5-61dc70f57c53",
			"tracking_id": 5,
			"class_name": "c_3",
			"annotation_type": "box",
			"annotation": {
				"coord": {
					"x": 1599.8942963181821,
					"y": 324.50907359605384,
					"width": 182.79495981111768,
					"height": 359.30661749135294
				},
				"meta": {
					"z_index": 5,
					"visible": true,
					"alpha": 1,
					"color": "#FFDFD5"
				}
			},
			"properties": []
		},
		{
			"id": "de1270e1-8aa8-44d1-8ccc-4003d098ac42",
			"class_id": "916ce2cb-6bee-423f-98a5-61dc70f57c53",
			"tracking_id": 6,
			"class_name": "c_3",
			"annotation_type": "box",
			"annotation": {
				"coord": {
					"x": 1281.0239825114495,
					"y": 436.7720808377029,
					"width": 397.08850884182584,
					"height": 385.72147213274536
				},
				"meta": {
					"z_index": 6,
					"visible": false,
					"alpha": 1,
					"color": "#FFDFD5"
				}
			},
			"properties": []
		}
	],
	"categories": {
		"properties": []
	},
	"Image": "A7C_20221118_046783.jpg",
	"Info": {
		"PLACE": "실내",
		"GPS": "35.478736/128.459071",
		"ADDRESS": "신구윗담길, 외부리, 창녕군, 경상남도, 50337, 대한민국",
		"METHOD": "A7C",
		"DATE": "2022-11-18",
		"DAY/NIGHT": "주간",
		"DEVICE": "HU205",
		"BRAND": "HUENTEK",
		"RESOLUTION": "1847/883",
		"COLOR": 1,
		"ROTATE": 0,
		"EXPOSURE": "0.002",
		"ISO": 0
	}
}