{
	"objects": [
		{
			"id": "0bbbefd8-d117-4fe0-a3a8-aa6e8243b6b3",
			"class_id": "916ce2cb-6bee-423f-98a5-61dc70f57c53",
			"tracking_id": 1,
			"class_name": "c_3",
			"annotation_type": "box",
			"annotation": {
				"coord": {
					"x": 629.3369982499726,
					"y": 179.52948329802342,
					"width": 536.6321101805815,
					"height": 370.3373662744229
				},
				"meta": {
					"z_index": 1,
					"visible": true,
					"alpha": 1,
					"color": "#FFDFD5"
				}
			},
			"properties": []
		},
		{
			"id": "6656922a-b9cc-4c6e-80d9-1243a2a19965",
			"class_id": "292c5b9c-e203-4ec1-9ca8-7579273fc70c",
			"tracking_id": 2,
			"class_name": "c_6",
			"annotation_type": "box",
			"annotation": {
				"coord": {
					"x": 1225.1414526767417,
					"y": 17.315578801607842,
					"width": 90.7989347861353,
					"height": 94.87982994055707
				},
				"meta": {
					"z_index": 2,
					"visible": true,
					"alpha": 1,
					"color": "#C9F6EA"
				}
			},
			"properties": []
		},
		{
			"id": "2c3d5373-adac-420a-b376-15161944ffd6",
			"class_id": "931b64ac-591e-4c5b-b88b-09e146d7c254",
			"tracking_id": 3,
			"class_name": "c_7",
			"annotation_type": "box",
			"annotation": {
				"coord": {
					"x": 1505.4710208153256,
					"y": 132.39112700047684,
					"width": 119.72802119837115,
					"height": 122.25754321750293
				},
				"meta": {
					"z_index": 3,
					"visible": true,
					"alpha": 1,
					"color": "#AFFFFF"
				}
			},
			"properties": []
		}
	],
	"categories": {
		"properties": []
	},
	"Image": "A7C_20221118_089986.jpg",
	"Info": {
		"PLACE": "실내",
		"GPS": "35.478736/128.459071",
		"ADDRESS": "신구윗담길, 외부리, 창녕군, 경상남도, 50337, 대한민국",
		"METHOD": "A7C",
		"DATE": "2022-11-18",
		"DAY/NIGHT": "주간",
		"DEVICE": "HU205",
		"BRAND": "HUENTEK",
		"RESOLUTION": "1847/883",
		"COLOR": 1,
		"ROTATE": 0,
		"EXPOSURE": "0.002",
		"ISO": 0
	}
}