{
	"objects": [
		{
			"id": "1e5d2250-f41d-4ff0-8d75-408c6176cc37",
			"class_id": "916ce2cb-6bee-423f-98a5-61dc70f57c53",
			"tracking_id": 1,
			"class_name": "c_3",
			"annotation_type": "box",
			"annotation": {
				"coord": {
					"x": 155.41371528758287,
					"y": 379.9522739357423,
					"width": 82.22343425977417,
					"height": 75.2627202483647
				},
				"meta": {
					"z_index": 1,
					"visible": true,
					"alpha": 1,
					"color": "#FFDFD5"
				}
			},
			"properties": []
		},
		{
			"id": "d7aac3da-7664-4d9b-867f-782aacd8007d",
			"class_id": "916ce2cb-6bee-423f-98a5-61dc70f57c53",
			"tracking_id": 2,
			"class_name": "c_3",
			"annotation_type": "box",
			"annotation": {
				"coord": {
					"x": 1342.5320869490602,
					"y": 0,
					"width": 308.4762408247818,
					"height": 350.6913932225966
				},
				"meta": {
					"z_index": 2,
					"visible": true,
					"alpha": 1,
					"color": "#FFDFD5"
				}
			},
			"properties": []
		},
		{
			"id": "c9f51156-650e-4ea7-9206-25c70bdd5deb",
			"class_id": "916ce2cb-6bee-423f-98a5-61dc70f57c53",
			"tracking_id": 3,
			"class_name": "c_3",
			"annotation_type": "box",
			"annotation": {
				"coord": {
					"x": 1502.3867215501377,
					"y": 227.1281338106968,
					"width": 269.59268105695196,
					"height": 373.28214740156284
				},
				"meta": {
					"z_index": 3,
					"visible": true,
					"alpha": 1,
					"color": "#FFDFD5"
				}
			},
			"properties": []
		}
	],
	"categories": {
		"properties": []
	},
	"Image": "A7C_20221118_085484.jpg",
	"Info": {
		"PLACE": "실내",
		"GPS": "35.478736/128.459071",
		"ADDRESS": "신구윗담길, 외부리, 창녕군, 경상남도, 50337, 대한민국",
		"METHOD": "A7C",
		"DATE": "2022-11-18",
		"DAY/NIGHT": "주간",
		"DEVICE": "HU205",
		"BRAND": "HUENTEK",
		"RESOLUTION": "1847/883",
		"COLOR": 1,
		"ROTATE": 0,
		"EXPOSURE": "0.002",
		"ISO": 0
	}
}