{
	"objects": [
		{
			"id": "ba1fc121-7918-4f30-bfb2-0a5b67a9043e",
			"class_id": "916ce2cb-6bee-423f-98a5-61dc70f57c53",
			"tracking_id": 1,
			"class_name": "c_3",
			"annotation_type": "box",
			"annotation": {
				"coord": {
					"x": 27.79325920145547,
					"y": 3.0553426261606376,
					"width": 270.9701081973226,
					"height": 215.27072865220137
				},
				"meta": {
					"z_index": 1,
					"visible": true,
					"alpha": 1,
					"color": "#FFDFD5"
				}
			},
			"properties": []
		},
		{
			"id": "35388ab4-513b-4e8d-957b-334c33ad36f8",
			"class_id": "916ce2cb-6bee-423f-98a5-61dc70f57c53",
			"tracking_id": 2,
			"class_name": "c_3",
			"annotation_type": "box",
			"annotation": {
				"coord": {
					"x": 256.6124674217997,
					"y": 3.0553426261606376,
					"width": 517.8539730696727,
					"height": 276.99161734511904
				},
				"meta": {
					"z_index": 2,
					"visible": true,
					"alpha": 1,
					"color": "#FFDFD5"
				}
			},
			"properties": []
		},
		{
			"id": "93779af7-9a18-4e5b-bd70-393e22ae556f",
			"class_id": "916ce2cb-6bee-423f-98a5-61dc70f57c53",
			"tracking_id": 3,
			"class_name": "c_3",
			"annotation_type": "box",
			"annotation": {
				"coord": {
					"x": 0.6962483817232155,
					"y": 173.1643521231772,
					"width": 558.4995409827177,
					"height": 636.7797025802615
				},
				"meta": {
					"z_index": 3,
					"visible": true,
					"alpha": 1,
					"color": "#FFDFD5"
				}
			},
			"properties": []
		},
		{
			"id": "e43e110a-40ed-4f3d-9792-c5b36dd092bf",
			"class_id": "916ce2cb-6bee-423f-98a5-61dc70f57c53",
			"tracking_id": 4,
			"class_name": "c_3",
			"annotation_type": "box",
			"annotation": {
				"coord": {
					"x": 1522.6450055288694,
					"y": 334.2409816107442,
					"width": 213.76542242999108,
					"height": 337.20725149927335
				},
				"meta": {
					"z_index": 4,
					"visible": true,
					"alpha": 1,
					"color": "#FFDFD5"
				}
			},
			"properties": []
		},
		{
			"id": "eee0ef7c-f0b9-4c10-8bfc-eb96db962421",
			"class_id": "916ce2cb-6bee-423f-98a5-61dc70f57c53",
			"tracking_id": 5,
			"class_name": "c_3",
			"annotation_type": "box",
			"annotation": {
				"coord": {
					"x": 1057.4796186678345,
					"y": 725.6423581163751,
					"width": 284.5187169740818,
					"height": 157.35764188362486
				},
				"meta": {
					"z_index": 5,
					"visible": true,
					"alpha": 1,
					"color": "#FFDFD5"
				}
			},
			"properties": []
		},
		{
			"id": "ebbcd10e-0a2c-4dbb-83a2-e580851b1dc4",
			"class_id": "916ce2cb-6bee-423f-98a5-61dc70f57c53",
			"tracking_id": 6,
			"class_name": "c_3",
			"annotation_type": "box",
			"annotation": {
				"coord": {
					"x": 1402.2138922709007,
					"y": 734.6746606006548,
					"width": 308.60475356526786,
					"height": 148.32533939934524
				},
				"meta": {
					"z_index": 6,
					"visible": true,
					"alpha": 1,
					"color": "#FFDFD5"
				}
			},
			"properties": []
		},
		{
			"id": "9b9407b3-d152-4d4e-879a-d490d46e0c4e",
			"class_id": "916ce2cb-6bee-423f-98a5-61dc70f57c53",
			"tracking_id": 7,
			"class_name": "c_3",
			"annotation_type": "box",
			"annotation": {
				"coord": {
					"x": 1648.9406632945506,
					"y": 812.4775593183317,
					"width": 100.6945107684578,
					"height": 70.52244068166829
				},
				"meta": {
					"z_index": 7,
					"visible": true,
					"alpha": 1,
					"color": "#FFDFD5"
				}
			},
			"properties": []
		}
	],
	"categories": {
		"properties": []
	},
	"Image": "A7C_20221118_080446.jpg",
	"Info": {
		"PLACE": "실내",
		"GPS": "35.478736/128.459071",
		"ADDRESS": "신구윗담길, 외부리, 창녕군, 경상남도, 50337, 대한민국",
		"METHOD": "A7C",
		"DATE": "2022-11-18",
		"DAY/NIGHT": "주간",
		"DEVICE": "HU205",
		"BRAND": "HUENTEK",
		"RESOLUTION": "1847/883",
		"COLOR": 1,
		"ROTATE": 0,
		"EXPOSURE": "0.002",
		"ISO": 0
	}
}