{
	"objects": [
		{
			"id": "652a4d92-94cd-4cdd-b613-5ffc9e52f6a1",
			"class_id": "916ce2cb-6bee-423f-98a5-61dc70f57c53",
			"tracking_id": 1,
			"class_name": "c_3",
			"annotation_type": "box",
			"annotation": {
				"coord": {
					"x": 758.0643644977423,
					"y": 0,
					"width": 262.5094381523429,
					"height": 454.48874824191273
				},
				"meta": {
					"z_index": 0,
					"visible": true,
					"alpha": 1,
					"color": "#FFDFD5"
				}
			},
			"properties": []
		},
		{
			"id": "ca374d23-ec9a-42fc-be17-c57c4201f622",
			"class_id": "916ce2cb-6bee-423f-98a5-61dc70f57c53",
			"tracking_id": 2,
			"class_name": "c_3",
			"annotation_type": "box",
			"annotation": {
				"coord": {
					"x": 992.83,
					"y": 1.51,
					"width": 291.62047745947154,
					"height": 303.25
				},
				"meta": {
					"z_index": 0,
					"visible": true,
					"alpha": 1,
					"color": "#FFDFD5"
				}
			},
			"properties": []
		},
		{
			"id": "d40dffa6-1b9b-4275-a288-39d990c045ff",
			"class_id": "916ce2cb-6bee-423f-98a5-61dc70f57c53",
			"tracking_id": 4,
			"class_name": "c_3",
			"annotation_type": "box",
			"annotation": {
				"coord": {
					"x": 556.17,
					"y": 0.56,
					"width": 282.62,
					"height": 89.41
				},
				"meta": {
					"z_index": 0,
					"visible": true,
					"alpha": 1,
					"color": "#FFDFD5"
				}
			},
			"properties": []
		},
		{
			"id": "e93fcef7-8933-4de0-a6b4-a1ccc8427461",
			"class_id": "06852717-c0c4-4200-a1ae-3648413cc30a",
			"tracking_id": 5,
			"class_name": "c_3_01",
			"annotation_type": "box",
			"annotation": {
				"coord": {
					"x": 785.4090976386113,
					"y": 274.01350951217705,
					"width": 286.5409023613887,
					"height": 279.33649048782297
				},
				"meta": {
					"z_index": 0,
					"visible": true,
					"alpha": 1,
					"color": "#D1C8FF"
				}
			},
			"properties": []
		},
		{
			"id": "b075bca0-7503-4ea2-81e9-8021ccad533d",
			"class_id": "916ce2cb-6bee-423f-98a5-61dc70f57c53",
			"tracking_id": 7,
			"class_name": "c_3",
			"annotation_type": "box",
			"annotation": {
				"coord": {
					"x": 1054.7547190761716,
					"y": 0,
					"width": 325.1152809238283,
					"height": 108.12
				},
				"meta": {
					"z_index": 0,
					"visible": true,
					"alpha": 1,
					"color": "#FFDFD5"
				}
			},
			"properties": []
		}
	],
	"categories": {
		"properties": []
	},
	"Image": "A7C_20221118_017701.jpg",
	"Info": {
		"PLACE": "실내",
		"GPS": "35.478736/128.459071",
		"ADDRESS": "신구윗담길, 외부리, 창녕군, 경상남도, 50337, 대한민국",
		"METHOD": "A7C",
		"DATE": "2022-11-18",
		"DAY/NIGHT": "주간",
		"DEVICE": "HU205",
		"BRAND": "HUENTEK",
		"RESOLUTION": "1847/883",
		"COLOR": 1,
		"ROTATE": 0,
		"EXPOSURE": "0.002",
		"ISO": 0
	}
}