{
	"objects": [
		{
			"id": "a83b1eb8-3d1e-456e-b2f5-44d0662f7f03",
			"class_id": "916ce2cb-6bee-423f-98a5-61dc70f57c53",
			"tracking_id": 1,
			"class_name": "c_3",
			"annotation_type": "box",
			"annotation": {
				"coord": {
					"x": 199.27282220743544,
					"y": 619.0714310956779,
					"width": 120.97107483324768,
					"height": 97.64093897254986
				},
				"meta": {
					"z_index": 1,
					"visible": true,
					"alpha": 1,
					"color": "#FFDFD5"
				}
			},
			"properties": []
		},
		{
			"id": "405587a0-1a96-4427-8800-3b6ee24f0c31",
			"class_id": "e0925dc8-44f6-4bf4-b3ee-7c6d4ae7524a",
			"tracking_id": 2,
			"class_name": "c_1_01",
			"annotation_type": "box",
			"annotation": {
				"coord": {
					"x": 916.0864274890964,
					"y": 380.0562651286419,
					"width": 155.406435482583,
					"height": 62.99457805412544
				},
				"meta": {
					"z_index": 2,
					"visible": true,
					"alpha": 1,
					"color": "#D5EBFF"
				}
			},
			"properties": []
		}
	],
	"categories": {
		"properties": []
	},
	"Image": "A7C_20221118_090012.jpg",
	"Info": {
		"PLACE": "실내",
		"GPS": "35.478736/128.459071",
		"ADDRESS": "신구윗담길, 외부리, 창녕군, 경상남도, 50337, 대한민국",
		"METHOD": "A7C",
		"DATE": "2022-11-18",
		"DAY/NIGHT": "주간",
		"DEVICE": "HU205",
		"BRAND": "HUENTEK",
		"RESOLUTION": "1847/883",
		"COLOR": 1,
		"ROTATE": 0,
		"EXPOSURE": "0.002",
		"ISO": 0
	}
}