{
	"objects": [
		{
			"id": "5e01dce3-40cb-4a1e-81c5-3fe7fa7f4598",
			"class_id": "916ce2cb-6bee-423f-98a5-61dc70f57c53",
			"tracking_id": 1,
			"class_name": "c_3",
			"annotation_type": "box",
			"annotation": {
				"coord": {
					"x": 669.2317987619299,
					"y": 0,
					"width": 269.51100681392654,
					"height": 339.7056514376556
				},
				"meta": {
					"z_index": 1,
					"visible": true,
					"alpha": 1,
					"color": "#FFDFD5"
				}
			},
			"properties": []
		},
		{
			"id": "ae1c6508-78ab-4e36-8002-0b4b79052ba7",
			"class_id": "916ce2cb-6bee-423f-98a5-61dc70f57c53",
			"tracking_id": 2,
			"class_name": "c_3",
			"annotation_type": "box",
			"annotation": {
				"coord": {
					"x": 858.9157933546759,
					"y": 0,
					"width": 262.3047641030936,
					"height": 266.19440737605305
				},
				"meta": {
					"z_index": 2,
					"visible": true,
					"alpha": 1,
					"color": "#FFDFD5"
				}
			},
			"properties": []
		},
		{
			"id": "190db7b4-cd3a-41aa-87d7-3cb2deb4a31b",
			"class_id": "916ce2cb-6bee-423f-98a5-61dc70f57c53",
			"tracking_id": 3,
			"class_name": "c_3",
			"annotation_type": "box",
			"annotation": {
				"coord": {
					"x": 1095.5124399340225,
					"y": 0,
					"width": 72.68407545821628,
					"height": 124.56564244024801
				},
				"meta": {
					"z_index": 3,
					"visible": true,
					"alpha": 1,
					"color": "#FFDFD5"
				}
			},
			"properties": []
		},
		{
			"id": "dabb4bf3-8ead-4523-be28-31a1053c05af",
			"class_id": "916ce2cb-6bee-423f-98a5-61dc70f57c53",
			"tracking_id": 4,
			"class_name": "c_3",
			"annotation_type": "box",
			"annotation": {
				"coord": {
					"x": 1161.576239122299,
					"y": 22.90143766589619,
					"width": 456.3287312038826,
					"height": 308.23133910214665
				},
				"meta": {
					"z_index": 4,
					"visible": true,
					"alpha": 1,
					"color": "#FFDFD5"
				}
			},
			"properties": []
		},
		{
			"id": "30859f9e-b4ca-40d9-9409-bcf904f231f6",
			"class_id": "916ce2cb-6bee-423f-98a5-61dc70f57c53",
			"tracking_id": 5,
			"class_name": "c_3",
			"annotation_type": "box",
			"annotation": {
				"coord": {
					"x": 1449.9257528770936,
					"y": 0,
					"width": 248.29221055520702,
					"height": 150.80568955331032
				},
				"meta": {
					"z_index": 5,
					"visible": true,
					"alpha": 1,
					"color": "#FFDFD5"
				}
			},
			"properties": []
		},
		{
			"id": "708e5484-a670-4779-9077-221dc853b066",
			"class_id": "916ce2cb-6bee-423f-98a5-61dc70f57c53",
			"tracking_id": 6,
			"class_name": "c_3",
			"annotation_type": "box",
			"annotation": {
				"coord": {
					"x": 976.1996922194936,
					"y": 267.52811702979034,
					"width": 767.6018258787004,
					"height": 285.9495747613514
				},
				"meta": {
					"z_index": 6,
					"visible": true,
					"alpha": 1,
					"color": "#FFDFD5"
				}
			},
			"properties": []
		},
		{
			"id": "1dc9049a-da4e-4fc2-af0e-89d51f8cdd6a",
			"class_id": "916ce2cb-6bee-423f-98a5-61dc70f57c53",
			"tracking_id": 7,
			"class_name": "c_3",
			"annotation_type": "box",
			"annotation": {
				"coord": {
					"x": 1256.685303194129,
					"y": 505.7841778780633,
					"width": 192.3439804697207,
					"height": 377.2158221219367
				},
				"meta": {
					"z_index": 7,
					"visible": true,
					"alpha": 1,
					"color": "#FFDFD5"
				}
			},
			"properties": []
		},
		{
			"id": "5ff5e236-030b-477b-94a3-e875d13d5273",
			"class_id": "06852717-c0c4-4200-a1ae-3648413cc30a",
			"tracking_id": 8,
			"class_name": "c_3_01",
			"annotation_type": "box",
			"annotation": {
				"coord": {
					"x": 684.6493836875615,
					"y": 462.09350963231884,
					"width": 486.97022671344723,
					"height": 231.65820973269228
				},
				"meta": {
					"z_index": 8,
					"visible": true,
					"alpha": 1,
					"color": "#D1C8FF"
				}
			},
			"properties": []
		},
		{
			"id": "6ea3b069-a2e1-442a-a640-84f1e6593aef",
			"class_id": "0dd3391f-3e08-4027-940b-618d1c3d443a",
			"tracking_id": 9,
			"class_name": "c_2_02_01",
			"annotation_type": "box",
			"annotation": {
				"coord": {
					"x": 649.613591837424,
					"y": 691.7218957007507,
					"width": 282.3226485651968,
					"height": 191.27810429924932
				},
				"meta": {
					"z_index": 9,
					"visible": true,
					"alpha": 1,
					"color": "#CED7FF"
				}
			},
			"properties": []
		},
		{
			"id": "ed590d89-18c2-4b92-bb55-54e94ae98076",
			"class_id": "292c5b9c-e203-4ec1-9ca8-7579273fc70c",
			"tracking_id": 11,
			"class_name": "c_6",
			"annotation_type": "box",
			"annotation": {
				"coord": {
					"x": 1539.9756868366612,
					"y": 551.0128956214329,
					"width": 222.1830780931391,
					"height": 248.9608314797689
				},
				"meta": {
					"z_index": 11,
					"visible": true,
					"alpha": 1,
					"color": "#C9F6EA"
				}
			},
			"properties": []
		},
		{
			"id": "7480c788-75bc-49c8-aa7f-f621303d2e09",
			"class_id": "292c5b9c-e203-4ec1-9ca8-7579273fc70c",
			"tracking_id": 10,
			"class_name": "c_6",
			"annotation_type": "box",
			"annotation": {
				"coord": {
					"x": 1341.5627323419458,
					"y": 0,
					"width": 114.98571738672399,
					"height": 46.48347099462214
				},
				"meta": {
					"z_index": 10,
					"visible": true,
					"alpha": 1,
					"color": "#C9F6EA"
				}
			},
			"properties": []
		}
	],
	"categories": {
		"properties": []
	},
	"Image": "A7C_20221118_008101.jpg",
	"Info": {
		"PLACE": "실내",
		"GPS": "35.478736/128.459071",
		"ADDRESS": "신구윗담길, 외부리, 창녕군, 경상남도, 50337, 대한민국",
		"METHOD": "A7C",
		"DATE": "2022-11-18",
		"DAY/NIGHT": "주간",
		"DEVICE": "HU205",
		"BRAND": "HUENTEK",
		"RESOLUTION": "1847/883",
		"COLOR": 1,
		"ROTATE": 0,
		"EXPOSURE": "0.002",
		"ISO": 0
	}
}