{
	"objects": [
		{
			"id": "b2c135b8-776c-4ec8-92c7-e03dd9279914",
			"class_id": "06852717-c0c4-4200-a1ae-3648413cc30a",
			"tracking_id": 1,
			"class_name": "c_3_01",
			"annotation_type": "box",
			"annotation": {
				"coord": {
					"x": 1096.895180366647,
					"y": 210.07887344766414,
					"width": 374.0966883500887,
					"height": 226.64251921939677
				},
				"meta": {
					"z_index": 1,
					"visible": true,
					"alpha": 1,
					"color": "#D1C8FF"
				}
			},
			"properties": []
		},
		{
			"id": "83a5e134-2051-4bc0-8ca4-bf3b5a219ffc",
			"class_id": "916ce2cb-6bee-423f-98a5-61dc70f57c53",
			"tracking_id": 2,
			"class_name": "c_3",
			"annotation_type": "box",
			"annotation": {
				"coord": {
					"x": 1150.142519219397,
					"y": 74.9125517445299,
					"width": 370.0007392075695,
					"height": 217.08530455351863
				},
				"meta": {
					"z_index": 2,
					"visible": true,
					"alpha": 1,
					"color": "#FFDFD5"
				}
			},
			"properties": []
		},
		{
			"id": "705afd8d-bb0b-4f4a-bf57-a3eb3d40841d",
			"class_id": "916ce2cb-6bee-423f-98a5-61dc70f57c53",
			"tracking_id": 3,
			"class_name": "c_3",
			"annotation_type": "box",
			"annotation": {
				"coord": {
					"x": 1267.5597279716146,
					"y": 439.1641780011828,
					"width": 255.31416321703114,
					"height": 405.78681253696027
				},
				"meta": {
					"z_index": 2,
					"visible": true,
					"alpha": 1,
					"color": "#FFDFD5"
				}
			},
			"properties": []
		},
		{
			"id": "eed3e06e-90e0-44a3-8af4-27dcefc2c15b",
			"class_id": "916ce2cb-6bee-423f-98a5-61dc70f57c53",
			"tracking_id": 4,
			"class_name": "c_3",
			"annotation_type": "box",
			"annotation": {
				"coord": {
					"x": 1025.610881135423,
					"y": 343.3041839148432,
					"width": 326.5984624482553,
					"height": 228.58353045535205
				},
				"meta": {
					"z_index": 2,
					"visible": true,
					"alpha": 1,
					"color": "#FFDFD5"
				}
			},
			"properties": []
		},
		{
			"id": "fc084912-a659-42e9-b6aa-361ff7f8c7c8",
			"class_id": "916ce2cb-6bee-423f-98a5-61dc70f57c53",
			"tracking_id": 5,
			"class_name": "c_3",
			"annotation_type": "box",
			"annotation": {
				"coord": {
					"x": 1017.7068302779421,
					"y": 569.6588557066823,
					"width": 271.6979597871082,
					"height": 313.3411442933177
				},
				"meta": {
					"z_index": 2,
					"visible": true,
					"alpha": 1,
					"color": "#FFDFD5"
				}
			},
			"properties": []
		},
		{
			"id": "338707da-d023-40c0-a14a-2a931c34ef5b",
			"class_id": "931b64ac-591e-4c5b-b88b-09e146d7c254",
			"tracking_id": 6,
			"class_name": "c_7",
			"annotation_type": "box",
			"annotation": {
				"coord": {
					"x": 198.5170017740983,
					"y": 794.4342844470727,
					"width": 121.51315789473679,
					"height": 88.56571555292726
				},
				"meta": {
					"z_index": 3,
					"visible": true,
					"alpha": 1,
					"color": "#AFFFFF"
				}
			},
			"properties": []
		},
		{
			"id": "3f0189d2-9007-4e51-bf31-25c81a41565b",
			"class_id": "292c5b9c-e203-4ec1-9ca8-7579273fc70c",
			"tracking_id": 7,
			"class_name": "c_6",
			"annotation_type": "box",
			"annotation": {
				"coord": {
					"x": 1490.3949542441662,
					"y": 304.1266234394348,
					"width": 48.38842993329922,
					"height": 218.61201380579752
				},
				"meta": {
					"z_index": 4,
					"visible": true,
					"alpha": 1,
					"color": "#C9F6EA"
				}
			},
			"properties": []
		}
	],
	"categories": {
		"properties": []
	},
	"Image": "A7C_20221118_083230.jpg",
	"Info": {
		"PLACE": "실내",
		"GPS": "35.478736/128.459071",
		"ADDRESS": "신구윗담길, 외부리, 창녕군, 경상남도, 50337, 대한민국",
		"METHOD": "A7C",
		"DATE": "2022-11-18",
		"DAY/NIGHT": "주간",
		"DEVICE": "HU205",
		"BRAND": "HUENTEK",
		"RESOLUTION": "1847/883",
		"COLOR": 1,
		"ROTATE": 0,
		"EXPOSURE": "0.002",
		"ISO": 0
	}
}