{
	"objects": [
		{
			"id": "f2de8d31-d96d-4e80-a1ca-c283ba0b8936",
			"class_id": "916ce2cb-6bee-423f-98a5-61dc70f57c53",
			"tracking_id": 1,
			"class_name": "c_3",
			"annotation_type": "box",
			"annotation": {
				"coord": {
					"x": 100.21422235363704,
					"y": 0,
					"width": 137.8969544648137,
					"height": 106.31482850384396
				},
				"meta": {
					"z_index": 1,
					"visible": true,
					"alpha": 1,
					"color": "#FFDFD5"
				}
			},
			"properties": []
		},
		{
			"id": "b8163753-43bc-4bd9-a949-e4ea3172ca83",
			"class_id": "916ce2cb-6bee-423f-98a5-61dc70f57c53",
			"tracking_id": 2,
			"class_name": "c_3",
			"annotation_type": "box",
			"annotation": {
				"coord": {
					"x": 912.5774689532822,
					"y": 63.990020697811985,
					"width": 282.62049083382624,
					"height": 440.99719101123594
				},
				"meta": {
					"z_index": 2,
					"visible": true,
					"alpha": 1,
					"color": "#FFDFD5"
				}
			},
			"properties": []
		},
		{
			"id": "6c27094c-6035-4d8d-b164-6dfbf62544b9",
			"class_id": "916ce2cb-6bee-423f-98a5-61dc70f57c53",
			"tracking_id": 3,
			"class_name": "c_3",
			"annotation_type": "box",
			"annotation": {
				"coord": {
					"x": 571.2483737433473,
					"y": 606.0206238911887,
					"width": 305.8308693081017,
					"height": 276.97937610881127
				},
				"meta": {
					"z_index": 3,
					"visible": true,
					"alpha": 1,
					"color": "#FFDFD5"
				}
			},
			"properties": []
		},
		{
			"id": "134f2f8e-d52d-45b9-8e3a-ebba8634b621",
			"class_id": "916ce2cb-6bee-423f-98a5-61dc70f57c53",
			"tracking_id": 4,
			"class_name": "c_3",
			"annotation_type": "box",
			"annotation": {
				"coord": {
					"x": 61.98536369012431,
					"y": 506.3525280898877,
					"width": 282.6204908338261,
					"height": 376.6474719101123
				},
				"meta": {
					"z_index": 4,
					"visible": true,
					"alpha": 1,
					"color": "#FFDFD5"
				}
			},
			"properties": []
		},
		{
			"id": "f787e45b-42ae-4d0a-b9d7-c945928dff6c",
			"class_id": "292c5b9c-e203-4ec1-9ca8-7579273fc70c",
			"tracking_id": 5,
			"class_name": "c_6",
			"annotation_type": "box",
			"annotation": {
				"coord": {
					"x": 1020.1797685794004,
					"y": 0,
					"width": 307.4538801491626,
					"height": 89.93103193376706
				},
				"meta": {
					"z_index": 5,
					"visible": true,
					"alpha": 1,
					"color": "#C9F6EA"
				}
			},
			"properties": []
		}
	],
	"categories": {
		"properties": []
	},
	"Image": "A7C_20221118_090650.jpg",
	"Info": {
		"PLACE": "실내",
		"GPS": "35.478736/128.459071",
		"ADDRESS": "신구윗담길, 외부리, 창녕군, 경상남도, 50337, 대한민국",
		"METHOD": "A7C",
		"DATE": "2022-11-18",
		"DAY/NIGHT": "주간",
		"DEVICE": "HU205",
		"BRAND": "HUENTEK",
		"RESOLUTION": "1847/883",
		"COLOR": 1,
		"ROTATE": 0,
		"EXPOSURE": "0.002",
		"ISO": 0
	}
}