{
	"objects": [
		{
			"id": "3beb3829-1d2a-4060-b60d-bdaaf01298aa",
			"class_id": "916ce2cb-6bee-423f-98a5-61dc70f57c53",
			"tracking_id": 2,
			"class_name": "c_3",
			"annotation_type": "box",
			"annotation": {
				"coord": {
					"x": 933.1,
					"y": 415.48,
					"width": 464.05000000000007,
					"height": 286.74
				},
				"meta": {
					"z_index": 0,
					"visible": true,
					"alpha": 1,
					"color": "#FFDFD5"
				}
			},
			"properties": []
		},
		{
			"id": "8e5fcb4e-93a7-4c38-b3cd-af5776c087cc",
			"class_id": "06852717-c0c4-4200-a1ae-3648413cc30a",
			"tracking_id": 3,
			"class_name": "c_3_01",
			"annotation_type": "box",
			"annotation": {
				"coord": {
					"x": 1374.73,
					"y": 419.84,
					"width": 374.96000000000004,
					"height": 364.21999999999997
				},
				"meta": {
					"z_index": 0,
					"visible": true,
					"alpha": 1,
					"color": "#D1C8FF"
				}
			},
			"properties": []
		},
		{
			"id": "2afdd0fe-088b-4711-afb2-327ccc7ba489",
			"class_id": "916ce2cb-6bee-423f-98a5-61dc70f57c53",
			"tracking_id": 4,
			"class_name": "c_3",
			"annotation_type": "box",
			"annotation": {
				"coord": {
					"x": 1267.24,
					"y": 43.83,
					"width": 320.9000000000001,
					"height": 397.18
				},
				"meta": {
					"z_index": 0,
					"visible": true,
					"alpha": 1,
					"color": "#FFDFD5"
				}
			},
			"properties": []
		},
		{
			"id": "3cd33c4b-684f-48ae-a57e-fead2b62a22a",
			"class_id": "916ce2cb-6bee-423f-98a5-61dc70f57c53",
			"tracking_id": 6,
			"class_name": "c_3",
			"annotation_type": "box",
			"annotation": {
				"coord": {
					"x": 246.49,
					"y": 616.93,
					"width": 363.26,
					"height": 264.21000000000004
				},
				"meta": {
					"z_index": 0,
					"visible": true,
					"alpha": 1,
					"color": "#FFDFD5"
				}
			},
			"properties": []
		},
		{
			"id": "cb17c0ca-51a2-4538-a1f8-44f187ea774f",
			"class_id": "916ce2cb-6bee-423f-98a5-61dc70f57c53",
			"tracking_id": 8,
			"class_name": "c_3",
			"annotation_type": "box",
			"annotation": {
				"coord": {
					"x": 1158.27,
					"y": 605.65,
					"width": 330.99,
					"height": 225.01999999999998
				},
				"meta": {
					"z_index": 0,
					"visible": true,
					"alpha": 1,
					"color": "#FFDFD5"
				}
			},
			"properties": []
		},
		{
			"id": "a892206d-d597-4826-b715-6803d824ae51",
			"class_id": "06852717-c0c4-4200-a1ae-3648413cc30a",
			"tracking_id": 9,
			"class_name": "c_3_01",
			"annotation_type": "box",
			"annotation": {
				"coord": {
					"x": 1003.91,
					"y": 177.36,
					"width": 251.04000000000008,
					"height": 244.45999999999998
				},
				"meta": {
					"z_index": 0,
					"visible": true,
					"alpha": 1,
					"color": "#D1C8FF"
				}
			},
			"properties": []
		},
		{
			"id": "c65edc7d-214b-4bdb-b4a9-ab6362f782f5",
			"class_id": "16b79171-1eef-4a2c-848d-bd084adab037",
			"tracking_id": 10,
			"class_name": "c_8_01",
			"annotation_type": "box",
			"annotation": {
				"coord": {
					"x": 1155.0415412527327,
					"y": 761.0089911153461,
					"width": 242.65089324610562,
					"height": 100.51559101399778
				},
				"meta": {
					"z_index": 1,
					"visible": true,
					"alpha": 1,
					"color": "#00C742"
				}
			},
			"properties": []
		}
	],
	"categories": {
		"properties": []
	},
	"Image": "A7C_20221118_013965.jpg",
	"Info": {
		"PLACE": "실내",
		"GPS": "35.478736/128.459071",
		"ADDRESS": "신구윗담길, 외부리, 창녕군, 경상남도, 50337, 대한민국",
		"METHOD": "A7C",
		"DATE": "2022-11-18",
		"DAY/NIGHT": "주간",
		"DEVICE": "HU205",
		"BRAND": "HUENTEK",
		"RESOLUTION": "1847/883",
		"COLOR": 1,
		"ROTATE": 0,
		"EXPOSURE": "0.002",
		"ISO": 0
	}
}