{
	"objects": [
		{
			"id": "5279f29e-a202-4e87-a0d9-c3432c39f8f0",
			"class_id": "292c5b9c-e203-4ec1-9ca8-7579273fc70c",
			"tracking_id": 1,
			"class_name": "c_6",
			"annotation_type": "box",
			"annotation": {
				"coord": {
					"x": 172.8870752831446,
					"y": 27.910911244355617,
					"width": 53.32222962469467,
					"height": 196.88207861425713
				},
				"meta": {
					"z_index": 1,
					"visible": true,
					"alpha": 1,
					"color": "#C9F6EA"
				}
			},
			"properties": []
		},
		{
			"id": "5884f39b-90c0-47b6-9177-6f6728d94f4c",
			"class_id": "292c5b9c-e203-4ec1-9ca8-7579273fc70c",
			"tracking_id": 2,
			"class_name": "c_6",
			"annotation_type": "box",
			"annotation": {
				"coord": {
					"x": 166.05089199792735,
					"y": 47.05222444296393,
					"width": 75.19801613738986,
					"height": 84.76867273669404
				},
				"meta": {
					"z_index": 2,
					"visible": true,
					"alpha": 1,
					"color": "#C9F6EA"
				}
			},
			"properties": []
		},
		{
			"id": "b9b14be8-753d-445b-83f6-9c48b76e8b6a",
			"class_id": "916ce2cb-6bee-423f-98a5-61dc70f57c53",
			"tracking_id": 3,
			"class_name": "c_3",
			"annotation_type": "box",
			"annotation": {
				"coord": {
					"x": 577.5891257680065,
					"y": 0,
					"width": 298.0575912354726,
					"height": 104.47616403878894
				},
				"meta": {
					"z_index": 3,
					"visible": true,
					"alpha": 1,
					"color": "#FFDFD5"
				}
			},
			"properties": []
		},
		{
			"id": "f795b846-5ad2-4a9e-a9d4-29a4a5a57fd2",
			"class_id": "916ce2cb-6bee-423f-98a5-61dc70f57c53",
			"tracking_id": 4,
			"class_name": "c_3",
			"annotation_type": "box",
			"annotation": {
				"coord": {
					"x": 827.7934340069584,
					"y": 0,
					"width": 598.8496557850323,
					"height": 245.30153971426452
				},
				"meta": {
					"z_index": 4,
					"visible": false,
					"alpha": 1,
					"color": "#FFDFD5"
				}
			},
			"properties": []
		}
	],
	"categories": {
		"properties": []
	},
	"Image": "A7C_20221118_008086.jpg",
	"Info": {
		"PLACE": "실내",
		"GPS": "35.478736/128.459071",
		"ADDRESS": "신구윗담길, 외부리, 창녕군, 경상남도, 50337, 대한민국",
		"METHOD": "A7C",
		"DATE": "2022-11-18",
		"DAY/NIGHT": "주간",
		"DEVICE": "HU205",
		"BRAND": "HUENTEK",
		"RESOLUTION": "1847/883",
		"COLOR": 1,
		"ROTATE": 0,
		"EXPOSURE": "0.002",
		"ISO": 0
	}
}