{
	"objects": [
		{
			"id": "b627bd66-7e25-4fd2-aac4-b9f4792f69ac",
			"class_id": "916ce2cb-6bee-423f-98a5-61dc70f57c53",
			"tracking_id": 1,
			"class_name": "c_3",
			"annotation_type": "box",
			"annotation": {
				"coord": {
					"x": 915.1018349596318,
					"y": 632.7555905210419,
					"width": 476.69117868186663,
					"height": 250.24440947895812
				},
				"meta": {
					"z_index": 1,
					"visible": true,
					"alpha": 1,
					"color": "#FFDFD5"
				}
			},
			"properties": []
		},
		{
			"id": "af25dff3-6970-4283-a37c-d8a5547ce977",
			"class_id": "916ce2cb-6bee-423f-98a5-61dc70f57c53",
			"tracking_id": 2,
			"class_name": "c_3",
			"annotation_type": "box",
			"annotation": {
				"coord": {
					"x": 1128.6421753716425,
					"y": 409.75121010973214,
					"width": 425.49593127861294,
					"height": 284.0159313098303
				},
				"meta": {
					"z_index": 2,
					"visible": true,
					"alpha": 1,
					"color": "#FFDFD5"
				}
			},
			"properties": []
		},
		{
			"id": "8f5c7457-20fe-4897-807b-9cd2eee2a86c",
			"class_id": "916ce2cb-6bee-423f-98a5-61dc70f57c53",
			"tracking_id": 3,
			"class_name": "c_3",
			"annotation_type": "box",
			"annotation": {
				"coord": {
					"x": 1544.8979866946693,
					"y": 550.4765212239267,
					"width": 186.97074674068926,
					"height": 332.52347877607326
				},
				"meta": {
					"z_index": 3,
					"visible": true,
					"alpha": 1,
					"color": "#FFDFD5"
				}
			},
			"properties": []
		}
	],
	"categories": {
		"properties": []
	},
	"Image": "A7C_20221118_070245.jpg",
	"Info": {
		"PLACE": "실내",
		"GPS": "35.478736/128.459071",
		"ADDRESS": "신구윗담길, 외부리, 창녕군, 경상남도, 50337, 대한민국",
		"METHOD": "A7C",
		"DATE": "2022-11-18",
		"DAY/NIGHT": "주간",
		"DEVICE": "HU205",
		"BRAND": "HUENTEK",
		"RESOLUTION": "1847/883",
		"COLOR": 1,
		"ROTATE": 0,
		"EXPOSURE": "0.002",
		"ISO": 0
	}
}